alchemynger/__init__.py
alchemynger/exception.py
alchemynger/manager.py
alchemynger/selector.py
alchemynger/sqlalchemy/__init__.py
alchemynger-0.2.2.dist-info/licenses/LICENSE
alchemynger-0.2.2.dist-info/METADATA
alchemynger-0.2.2.dist-info/WHEEL
alchemynger-0.2.2.dist-info/RECORD
