Metadata-Version: 2.4
Name: Alchemynger
Version: 0.2.2
Summary: Simple SQLAlchemy connector manager.
License-File: LICENSE
Keywords: SQLAlchemy,SQL,Database
Author: Resheba
Author-email: c90de11@gmail.com
Requires-Python: >=3.9
Classifier: License :: OSI Approved :: MIT License
Classifier: Programming Language :: Python :: 3
Classifier: Programming Language :: Python :: 3.9
Classifier: Programming Language :: Python :: 3.10
Classifier: Programming Language :: Python :: 3.11
Classifier: Programming Language :: Python :: 3.12
Classifier: Programming Language :: Python :: 3.13
Classifier: Programming Language :: Python :: 3.14
Requires-Dist: sqlalchemy (>=2.0.36,<3.0.0)
Project-URL: Repository, https://github.com/Resheba/Alchemynger
